setup.cfg
setup.py
pywin64/__init__.py
pywin64/dl.py
pywin64.egg-info/PKG-INFO
pywin64.egg-info/SOURCES.txt
pywin64.egg-info/dependency_links.txt
pywin64.egg-info/requires.txt
pywin64.egg-info/top_level.txt